{
    "bsonType": "object",
    "properties": {
        "CreatedAt": {
            "bsonType": "date"
        },
        "Email": {
            "bsonType": "string"
        },
        "FirstName": {
            "bsonType": "string"
        },
        "ImagePath": {
            "bsonType": "string"
        },
        "IsModerator": {
            "bsonType": "bool"
        },
        "LastName": {
            "bsonType": "string"
        },
        "Patronymic": {
            "bsonType": "string"
        },
        "Rate": {
            "bsonType": "long"
        },
        "RateWeight": {
            "bsonType": "long"
        },
        "Status": {
            "bsonType": "long"
        },
        "UpdatedAt": {
            "bsonType": "date"
        },
        "_id": {
            "bsonType": "objectId"
        }
    },
    "required": [
        "_id",
        "RateWeight",
        "Rate",
        "Status",
        "CreatedAt",
        "UpdatedAt"
    ],
    "title": "User"
}
